{
	"PV":{
		"DCM:Energy:RBV":{
			"pvname":"D08R1-MO-MC2:V-OH-ENERGY.RBV"
		},
		"DCM:Speed":{
			"pvname":"D08R1-MO-MC2:OH-DCM-STP-ROTX1.VELO"
		},
		"DCM:Encoder":{
			"pvname":"D08R1-MO-MC2:OH-DCM-STP-ROTX1.RRBV"
		},
		"ketek_erasestart":{
			"pvname":"D08-ES-SDD1:mca1.ERST"
		},
		"ketek_realtime":{
			"pvname":"D08-ES-SDD1:PresetReal"
		},
		"ICsAvrTime": {
			"pvname": "D08-ES-DAQ:setAveragingTime"
		},
		"PLOT:Energy":{
			"pvname":"PLOT:Energy"
		},
		"PLOT:I0":{
			"pvname":"PLOT:I0"
		},
		"PLOT:It":{
			"pvname":"PLOT:It"
		},
		"PLOT:It2":{
			"pvname":"PLOT:It2"
		},
		"PLOT:AbsTr":{
			"pvname":"PLOT:AbsTr"
		},
		"PLOT:AbsTr2":{
			"pvname":"PLOT:AbsTr2"
		},
		"PLOT:If":{
			"pvname":"PLOT:If"
		},
		"PLOT:AbsFlu":{
			"pvname":"PLOT:AbsFlu"
		},
		"USERINFO:Proposal":{
			"pvname":"USERINFO:Proposal"
		},
		"USERINFO:Email":{
			"pvname":"USERINFO:Email"
		},
		"USERINFO:Beamline":{
			"pvname":"USERINFO:Beamline"
		},
		"USERINFO:StartTime":{
			"pvname":"USERINFO:StartTime"
		},
		"USERINFO:EndTime":{
			"pvname":"USERINFO:EndTime"
		},
		"SCAN:pause":{
			"pvname":"SCAN:XAFSPause"
		},
		"SCAN:Nsamples":{
			"pvname":"SCAN:Nsamples"
		},
		"SCAN:CurrentSample":{
			"pvname":"SCAN:CurrentSample"
		},
		"SCAN:Nscans":{
			"pvname":"SCAN:Nscans"
		},
		"SCAN:CurrentScan":{
			"pvname":"SCAN:CurrentScan"
		},
		"SCAN:NIntervals":{
			"pvname":"SCAN:NIntervals"
		},
		"SCAN:CurrentInterval":{
			"pvname":"SCAN:CurrentInterval"
		},
		"RING:Current":{
		"pvname":"SRC01-DI-DCCT1:getDcctCurrent"
		},
		"SHUTTER1:Status":{
			"pvname":"FE08-VA-PHSH:getStatus"
		},
		"SHUTTER2:Status":{
			"pvname":"D08-OP-VA-PHSH:getStatus"
		},
		"STOPPER:Status":{
			"pvname":"FE08-VA-PHST:getStatus"
		},
		"ENGCAL:RealFoilEng":{
			"pvname":"XAFS:ENGCAL:RealFoilEleEng"
		},
		"ENGCAL:FoilElement":{
			"pvname":"XAFS:ENGCAL:FoilElement"
		},
		"BLSetup:Crystal":{
			"pvname":"XAFS:DCMSetup:Crystal"
		}
	},
	"Motors":{
		"DCM:Theta":{
			"pvname":"D08R1-MO-MC2:OH-DCM-STP-ROTX1"
		},
		"DCM:Energy:SP":{
			"pvname":"D08R1-MO-MC2:V-OH-ENERGY"
		},
		"DCM:Y":{
			"pvname":"D08R1-MO-MC2:OH-DCM-STP-TRSY1"
		},
		"SMP:X":{
			"pvname":"D08R2-MO-MC2:C-EH-SMP-Z1"
		},
		"SMP:Y":{
			"pvname":"D08R2-MO-MC2:B-EH-SMP-Y1"
		},
		"SMP:Rot":{
			"pvname":"D08R2-MO-MC2:D-EH-SMP-ROT"
		}
	}
}
